README.md
setup.py
docli/__init__.py
docli/main.py
docli.egg-info/PKG-INFO
docli.egg-info/SOURCES.txt
docli.egg-info/dependency_links.txt
docli.egg-info/entry_points.txt
docli.egg-info/requires.txt
docli.egg-info/top_level.txt
docli/commands/__init__.py
docli/commands/account.py
docli/commands/actions.py
docli/commands/base_request.py
docli/commands/domain.py
docli/commands/droplet.py
docli/commands/droplet_actions.py
docli/commands/image_actions.py
docli/commands/images.py
docli/commands/records.py
docli/commands/region_size.py
docli/commands/ssh_keys.py
docli/commands/urls.py