Metadata-Version: 1.1
Name: docli
Version: 1.6
Summary: Digital Ocean command line interface
Home-page: https://github.com/yspanchal/docli
Author: Yogesh Panchal
Author-email: yspanchal@gmail.com
License: UNKNOWN
Download-URL: https://github.com/yspanchal/docli/tarball/master
Platform: UNKNOWN
